polyrename/__init__.py
polyrename/__main__.py
polyrename/driver/__init__.py
polyrename/driver/dev/__init__.py
polyrename/driver/driver_dev.py
polyrename/driver/driver_gui.py
polyrename/driver/gui/__init__.py
polyrename/driver/gui/file_picker.py
polyrename/driver/gui/icons/128x128.png
polyrename/driver/gui/icons/16x16.png
polyrename/driver/gui/icons/256x256.png
polyrename/driver/gui/icons/32x32.png
polyrename/driver/gui/icons/64x64.png
polyrename/driver/gui/main_window.py
polyrename/driver/gui/pipeline_editor.py
polyrename/driver/gui/transformation_configuration.py
polyrename/driver/gui/transformation_library.py
polyrename/file_sequence.py
polyrename/transformation/__init__.py
polyrename/transformation/current_datetime.py
polyrename/transformation/date_time.py
polyrename/transformation/insert.py
polyrename/transformation/music_tags.py
polyrename/transformation/pipeline.py
polyrename/transformation/prefix.py
polyrename/transformation/regex_replace.py
polyrename/transformation/remove_range.py
polyrename/transformation/replace.py
polyrename/transformation/replace_extension.py
polyrename/transformation/sequence.py
polyrename/transformation/suffix.py
polyrename/transformation/transformation.py
polyrename/transformation/utils/__init__.py
polyrename/transformation/utils/path_utils.py
polyrename-1.1.0.dist-info/entry_points.txt
polyrename-1.1.0.dist-info/LICENSE
polyrename-1.1.0.dist-info/WHEEL
polyrename-1.1.0.dist-info/METADATA
polyrename-1.1.0.dist-info/RECORD
